[{"name": "cpython-install", "log_file": "/workdir/results/six/1.16.0/1/cpython-install.log", "reference_impl": true, "test_time": 0.917331, "installs": true}, {"name": "graalpy-install", "log_file": "/workdir/results/six/1.16.0/1/graalpy-install.log", "test_time": 5.635659, "installs": true}, {"name": "cpython-tox.ini", "log_file": "/workdir/results/six/1.16.0/1/cpython-tox-ini.log", "auxiliary": true}, {"name": "graalpy-tox.ini", "log_file": "/workdir/results/six/1.16.0/1/graalpy-tox-ini.log", "auxiliary": true}, {"name": "cpython-test", "log_file": "/workdir/results/six/1.16.0/1/cpython-test.log", "reference_impl": true, "test_time": 12.48128, "passed": 200, "failed": 0, "skipped": 0, "unknown": 0}, {"name": "graalpy-test", "log_file": "/workdir/results/six/1.16.0/1/graalpy-test.log", "test_time": 75.204649, "passed": 183, "failed": 1, "skipped": 16, "unknown": 0}]