[{"name": "cpython-install", "log_file": "/workdir/results/cmd2/2.4.3/1/cpython-install.log", "reference_impl": true, "test_time": 1.420273, "installs": true}, {"name": "graalpy-install", "log_file": "/workdir/results/cmd2/2.4.3/1/graalpy-install.log", "test_time": 11.663229, "installs": true}, {"name": "cpython-tox.ini", "log_file": "/workdir/results/cmd2/2.4.3/1/cpython-tox-ini.log", "auxiliary": true}, {"name": "graalpy-tox.ini", "log_file": "/workdir/results/cmd2/2.4.3/1/graalpy-tox-ini.log", "auxiliary": true}, {"name": "cpython-test", "log_file": "/workdir/results/cmd2/2.4.3/1/cpython-test.log", "reference_impl": true, "test_time": 31.875941}]